LimitFunc/LimitFunc.py
LimitFunc/__init__.py
LimitFunc-0.0.1.dist-info/LICENSE
LimitFunc-0.0.1.dist-info/METADATA
LimitFunc-0.0.1.dist-info/WHEEL
LimitFunc-0.0.1.dist-info/top_level.txt
LimitFunc-0.0.1.dist-info/RECORD
