Metadata-Version: 2.1
Name: LimitFunc
Version: 0.0.1
Summary: limit function args type
Home-page: https://github.com/lisztomania-Zero/LimitFunc
Author: lisztomania
Author-email: lisztomania@vip.qq.com
License: UNKNOWN
Platform: UNKNOWN
Classifier: Programming Language :: Python :: 3 :: Only
Classifier: License :: OSI Approved :: MIT License
Classifier: Operating System :: OS Independent
